{"guide_basic-concepts.md":"e5ff2a36","guide_consumption-methods.md":"a1023987","guide_embedded-csv-parser-serializer.md":"918f3ada","guide_error-handling.md":"8b17f169","guide_exstream-in-depth.md":"5f438551","guide_extending-exstream.md":"e6dd17f5","guide_forking-and-merging.md":"f73c6223","guide_getting-started.md":"c70c4cdb","guide_modularization.md":"11268645","guide_operations-on-sorted-data.md":"4973486d","guide_type-of-sources.md":"2a43049e","guide_what-is-exstream.md":"34872ffb","index.md":"36980674","reference_filter.md":"19d63b78","reference_through.md":"6ae01caa"}
